ocpeasy/__init__.py
ocpeasy/__main__.py
ocpeasy/__version__.py
ocpeasy/constants.py
ocpeasy/createStage.py
ocpeasy/deployStage.py
ocpeasy/destroyStage.py
ocpeasy/notify.py
ocpeasy/ocUtils.py
ocpeasy/scaffold.py
ocpeasy/utils.py
ocpeasy/utils_test.py
ocpeasy-0.1.20.dist-info/entry_points.txt
ocpeasy-0.1.20.dist-info/WHEEL
ocpeasy-0.1.20.dist-info/METADATA
ocpeasy-0.1.20.dist-info/RECORD
