Metadata-Version: 2.1
Name: ocpeasy
Version: 0.1.20
Summary: OCPeasy is an open-source software provisioning, configuration management, and application-deployment tool enabling infrastructure as code on OpenShift.
Home-page: https://www.ocpeasy.org
License: MIT
Author: David Barrat
Author-email: david.barrat@protonmail.com
Requires-Python: >=3.8,<4.0
Classifier: License :: OSI Approved :: MIT License
Classifier: Programming Language :: Python :: 3
Classifier: Programming Language :: Python :: 3.8
Classifier: Programming Language :: Python :: 3.9
Requires-Dist: GitPython (>=3.1.12,<4.0.0)
Requires-Dist: PyYAML (>=5.3.1,<6.0.0)
Requires-Dist: cryptography (==3.4.5)
Requires-Dist: fire (>=0.3.1,<0.4.0)
Requires-Dist: openshift-client (==1.0.12)
Requires-Dist: sh (>=1.14.1,<2.0.0)
Requires-Dist: simple-term-menu (>=0.10.4,<0.11.0)
Project-URL: Documentation, https://www.ocpeasy.org
Project-URL: Repository, https://github.com/ocpeasy/ocpeasy
